Metadata-Version: 2.1
Name: robotframework-awslibrary
Version: 0.0.2
Summary: A python package to create test cases for AWS services using Robot Framework
Home-page: https://github.com/Hespius/robotframework-awslibrary
Author: Vinicius Henrique Especoto
License: MIT Licence
Keywords: robotframework testing testautomation aws boto3
Platform: UNKNOWN
License-File: LICENSE
